holodeck/plot.py
holodeck/cyutils.pxd
holodeck/detstats.py
holodeck/version.txt
holodeck/hardening.py
holodeck/cyutils.c
holodeck/relations.py
holodeck/constants.py
holodeck/__init__.py
holodeck/extensions.py
holodeck/pop_observational.py
holodeck/accretion.py
holodeck/cyutils.pyx
holodeck/galaxy_profiles.py
holodeck/anisotropy.py
holodeck/cyutils.cpython-39-x86_64-linux-gnu.so
holodeck/single_sources.py
holodeck/gravwaves.py
holodeck/cyutils.html
holodeck/logger.py
holodeck/host_relations.py
holodeck/utils.py
holodeck/observations.py
holodeck/librarian/__init__.py
holodeck/librarian/posterior_populations.py
holodeck/librarian/gen_lib.py
holodeck/librarian/libraries.py
holodeck/librarian/param_spaces_classic.py
holodeck/librarian/combine.py
holodeck/librarian/param_spaces.py
holodeck/librarian/fit_spectra.py
holodeck/librarian/tests/test_libraries__param_space.py
holodeck/librarian/tests/test_param_spaces.py
holodeck/gps/plotting_utils.py
holodeck/gps/gp_utils.py
holodeck/gps/__init__.py
holodeck/gps/sam_utils.py
holodeck/ems/runnoe2012.py
holodeck/ems/__init__.py
holodeck/ems/basics.py
holodeck/ems/drw.py
holodeck/ems/tests/basics_sdss_bands_2023-09-05.json
holodeck/ems/tests/test_basics.py
holodeck/data/SHM06_scattering_experiments.json
holodeck/data/2mass_galaxies.lst
holodeck/data/illustris-galaxy-mergers_L75n1820FP_gas-100_dm-100_star-100_bh-000.hdf5
holodeck/data/added_Mks.lst
holodeck/data/mcconnell+ma-2013_1211.2816.txt
holodeck/data/README.md
holodeck/data/schutzMa_extension.txt
holodeck/data/observational_2mass_galaxy-catalog_extended.npz
holodeck/data/mbhb-pops-continuous_casey-clyde_mingarelli_2021-02-17.npz
holodeck/data/preferential_accretion/siwek+22/lambda_e=0.40.txt
holodeck/data/preferential_accretion/siwek+22/lambda_e=0.60.txt
holodeck/data/preferential_accretion/siwek+22/lambda_vs_q_e=0.00_e=0.20_e=0.40_e=0.60_e=0.80.png
holodeck/data/preferential_accretion/siwek+22/lambda_e=0.80.txt
holodeck_gw-1.5.2.dist-info/top_level.txt
holodeck_gw-1.5.2.dist-info/METADATA
holodeck_gw-1.5.2.dist-info/WHEEL
holodeck_gw-1.5.2.dist-info/entry_points.txt
holodeck_gw-1.5.2.dist-info/RECORD
holodeck_gw-1.5.2.dist-info/LICENSE
