Metadata-Version: 2.1
Name: holodeck-gw
Version: 1.5.2
Summary: holodeck: Massive black hole (MBH) binary simulator for pulsar timing array signals.
Home-page: https://github.com/NANOGrav/holodeck/
Author: NANOGrav
Author-email: luke.kelley@nanograv.org
License: MIT
Requires-Python: >=3.9
License-File: LICENSE
Requires-Dist: astropy
Requires-Dist: cosmopy
Requires-Dist: h5py
Requires-Dist: ipywidgets
Requires-Dist: kalepy
Requires-Dist: matplotlib
Requires-Dist: numpy
Requires-Dist: scipy
Requires-Dist: psutil
Requires-Dist: tqdm
Requires-Dist: cython <3.0.0
Requires-Dist: schwimmbad
Requires-Dist: emcee
Requires-Dist: george
Requires-Dist: sympy
Requires-Dist: hasasia
Requires-Dist: healpy
